pydsm.py
py_dsm-1.0.1.dist-info/LICENSE
py_dsm-1.0.1.dist-info/METADATA
py_dsm-1.0.1.dist-info/WHEEL
py_dsm-1.0.1.dist-info/top_level.txt
py_dsm-1.0.1.dist-info/RECORD
