Metadata-Version: 2.1
Name: py-dsm
Version: 1.0.1
Summary: Python true-shared memory parallel computation
Home-page: https://github.com/matloff/pydsm
Author: Daniel Guo, Norm Matloff
Author-email: zhyguo@ucdavis.edu, matloff@cs.ucdavis.edu
License: UNKNOWN
Keywords: shared memory parallel concurrent multiprocessing numpy
Platform: UNKNOWN
Classifier: Intended Audience :: Developers
Classifier: Intended Audience :: Science/Research
Classifier: License :: OSI Approved :: MIT License
Classifier: Topic :: Scientific/Engineering
Classifier: Operating System :: Unix
Classifier: Operating System :: POSIX
Classifier: Programming Language :: Python :: 2
Classifier: Programming Language :: Python :: 2.7
Classifier: Programming Language :: Python :: 3
Classifier: Programming Language :: Python :: 3.4
Classifier: Programming Language :: Python :: 3.5
Classifier: Programming Language :: Python :: 3.6
Classifier: Programming Language :: Python :: 3.7
Classifier: Programming Language :: Python :: 3.8
Requires-Dist: SharedArray
Requires-Dist: numpy
